stitchwell/__init__.py
stitchwell/stitchwell.py
stitchwell-2.1.dist-info/LICENSE
stitchwell-2.1.dist-info/METADATA
stitchwell-2.1.dist-info/WHEEL
stitchwell-2.1.dist-info/top_level.txt
stitchwell-2.1.dist-info/RECORD
